{
  "project_info": {
    "project_number": "1076650756662",
    "project_id": "egg-english-app",
    "storage_bucket": "egg-english-app.appspot.com"
  },
  "client": [
    {
      "client_info": {
        "mobilesdk_app_id": "1:1076650756662:android:fcbe6201c2c391e65fe697",
        "android_client_info": {
          "package_name": "com.bicontest.egg"
        }
      },
      "oauth_client": [
        {
          "client_id": "1076650756662-tl8tcsbjbghsigvk65kqu6lkbvonlmvq.apps.googleusercontent.com",
          "client_type": 3
        }
      ],
      "api_key": [
        {
          "current_key": "AIzaSyCAydygCknBvnbgiFp9YY4HlIoDpmPb3pA"
        }
      ],
      "services": {
        "appinvite_service": {
          "other_platform_oauth_client": [
            {
              "client_id": "1076650756662-tl8tcsbjbghsigvk65kqu6lkbvonlmvq.apps.googleusercontent.com",
              "client_type": 3
            }
          ]
        }
      }
    }
  ],
  "configuration_version": "1"
}